projeto/vhdl/transmissor/baud_rate_generator.vhdl
library ieee;
use ieee.std_logic_1164.all;
use ieee.numeric_std.all;

entity baud_rate_generator is
	port (
	    clock : in std_logic;
	    reset : in std_logic;
	    divisor : in std_logic_vector(15 downto 0);
	    baudOut_n: out std_logic
	);
end baud_rate_generator;

architecture Behavioral of baud_rate_generator is
   signal counter : std_logic_vector(15 downto 0) := (others => '0');
	signal out_clock : std_logic := '1';
begin
	process(clock, reset)
    begin
        if reset = '1' then
            counter <= (others => '0');
            out_clock <= '1';
        elsif rising_edge(clock) then
            if unsigned(counter) = unsigned('0' & divisor(15 downto 1)) then
                counter <= (others => '0');
                out_clock <= not out_clock;
            else
                counter <= std_logic_vector(unsigned(counter) + 1);
            end if;
        end if;
    end process;
	 baudOut_n <= out_clock;
end Behavioral;

projeto/vhdl/transmissor/shift_reg.vhd
library ieee;
use ieee.std_logic_1164.all;
use ieee.numeric_std.all;

entity shift_reg is
	generic(
		WIDTH:natural:=8 
	);
	port(
		clock,reset : in std_logic;	
		loadOrShift : in std_logic_vector(1 downto 0);
		serial_i: 	in  std_logic;				 
		data_i:		in  std_logic_vector(WIDTH - 1 downto 0);
		serial_o_r:	out std_logic;				 
		serial_o_l:	out std_logic
		);
end shift_reg;

architecture shift_reg_arch of shift_reg is
    signal reg : std_logic_vector(WIDTH - 1 downto 0); -- Registrador interno
begin
    process(clock, reset)
    begin
        if reset = '1' then
            -- Resetar o registrador
            reg <= (others => '1');
        elsif rising_edge(clock) then
            case loadOrShift is
                when "00" =>
                    -- retorna para o estado "11111111"
                    reg <= "11111111";
                when "01" =>
                    -- Deslocamento para a direita
                    reg <= serial_i & reg(WIDTH - 1 downto 1);
                when "10" =>
                    -- Deslocamento para a esquerda
                    reg <= reg(WIDTH - 2 downto 0) & serial_i;
                when "11" =>
                    -- Carga externa paralela
                    reg <= data_i;
                when others =>
                    -- Caso padrão (opcional)
                    reg <= reg;
            end case;
        end if;
    end process;

    -- Atribuir valores às saídas
    serial_o_r <= reg(0); -- Saída serial à direita
    serial_o_l <= reg(WIDTH - 1); -- Saída serial à esquerda
end shift_reg_arch;

projeto/vhdl/transmissor/transmitter_timing_control.vhd
library ieee;
use IEEE.std_logic_1164.all;
use IEEE.numeric_std.all;

entity transmitter_timing_control is
	port(
	    clock : in std_logic;
	    reset : in std_logic;
	    start  : in std_logic;
	    regControl : out std_logic_vector(1 downto 0);
			serial_i : out std_logic;
			done	: out std_logic;
			current_state : out std_logic_vector(3 downto 0)
	);
end transmitter_timing_control;

architecture arch_ttc of transmitter_timing_control is
	type states is (IDLE,START_BIT,D7,D6,D5,D4,D3,D2,D1,D0,END_BIT_1, END_BIT_2);
	signal state : states := IDLE;
	signal rc : std_logic_vector(1 downto 0);
begin

	regControl <= rc;
	with state select -- Substitua 'your_state_variable' pela sua variável de estado enumerada (e.g., present_state)
			current_state <= "0000" when IDLE, --0
											"0001" when START_BIT, --1
											"0010" when D0, --2
											"0011" when D1,
											"0100" when D2,
											"0101" when D3,
											"0110" when D4,
											"0111" when D5,
											"1000" when D6,
											"1001" when D7, --9
											"1010" when END_BIT_1, -- 10
											"1011" when END_BIT_2,
											"XXXX" when others;

	process(clock, reset)
	begin
		if reset = '1' then
			state <= IDLE;
		elsif falling_edge(clock) then
				case state is
				when IDLE =>
					-- no inicio o contador deve estar "1111111"
					rc <= "00";
					done <= '0';
					if start = '1' then
						state <= START_BIT;
					end if;
				-- Start bit
				when START_BIT =>
					rc <= "10";
					serial_i <= '0';
					state <= D0;
				-- load
				when D0 =>
					rc <= "11";
					state <= D1;
				when D1 =>
					rc <= "01";
					serial_i <= '1';
					state <= D2;
				when D2 =>
					rc <= "01";
					serial_i <= '1';
					state <= D3;
				when D3 =>
					rc <= "01";
					serial_i <= '1';
					state <= D4;
				when D4 =>
					rc <= "01";
					serial_i <= '1';
					state <= D5;
				when D5 =>
					rc <= "01";
					serial_i <= '1';
					state <= D6;
				when D6 =>
					rc <= "01";
					serial_i <= '1';
					state <= D7;
				when D7 =>
					rc <= "01";
					serial_i <= '1';
					state <= END_BIT_1;
				when END_BIT_1 =>
					rc <= "00";
					state <= END_BIT_2;
				when END_BIT_2 =>
					rc <= "00";
					done <= '1';
					if start = '1' then
						state <= IDLE;
					end if;
				when others =>
					rc <= "00";
				end case;
		end if;
	end process;
end arch_ttc;

projeto/vhdl/transmissor/control_unit_tx.vhd
library ieee;
use ieee.std_logic_1164.all;
use ieee.numeric_std.all;

entity control_unit_tx is
	port (
	    clock : in std_logic;
	    reset : in std_logic;
	    start : in std_logic;
	    dados : in std_logic_vector(7 downto 0);
	    sout  : out std_logic;
			done: out std_logic;
			current_state : out std_logic_vector(3 downto 0)
	);
end control_unit_tx;

architecture arch_tx of control_unit_tx is

	component transmitter_timing_control is
		port(
			clock : in std_logic;
			reset : in std_logic;
			start  : in std_logic;
			regControl : out std_logic_vector(1 downto 0);
			serial_i : out std_logic;
			done	: out std_logic;
			current_state : out std_logic_vector(3 downto 0)
		);
	end component;
	component shift_reg is
		generic(WIDTH:natural:=8);
		port(
			clock,reset : in std_logic;
			loadOrShift : in std_logic_vector(1 downto 0);
			serial_i: 	in  std_logic;
			data_i:		in  std_logic_vector(WIDTH - 1 downto 0);
			serial_o_r:	out std_logic;
			serial_o_l:	out std_logic
		);
	end component;


	signal loadOrShift 	: std_logic_vector(1 downto 0);
	signal dados_tx		: std_logic;
	signal serial_i 	: std_logic;


begin
	--- Saida principal
	sout <= dados_tx;

	TTC: transmitter_timing_control
	port map(clock=>clock, reset=>reset, regControl=>loadOrShift, serial_i=>serial_i, start=>start, done=>done, current_state=>current_state);

	REG: shift_reg
	port map(clock=>clock, reset=>reset, loadOrShift=>loadOrShift, serial_i=>serial_i, data_i=>dados, serial_o_r=>dados_tx);

end arch_tx;

projeto/vhdl/transmissor/tx.vhd
library ieee;
use ieee.std_logic_1164.all;
use ieee.numeric_std.all;

entity tx is
	port (
	    clock : in std_logic;
	    reset : in std_logic;
	    start : in std_logic;
	    dados : in std_logic_vector(255 downto 0);
	    sout  : out std_logic;
      ok    : out std_logic
	);
end tx;

architecture arch_tx of tx is
component control_unit_tx is
	port (
	    clock : in std_logic;
	    reset : in std_logic;
	    start : in std_logic;
	    dados : in std_logic_vector(7 downto 0);
	    sout  : out std_logic;
		  done: out std_logic;
      current_state : out std_logic_vector(3 downto 0)
	);
  end component;
	component baud_rate_generator is
	port(
	    clock : in std_logic;
	    reset : in std_logic;
	    divisor : in std_logic_vector(15 downto 0);
	    baudOut_n: out std_logic
    	);
	end component;

	type states is (O, T,
  L1_Q1,L2_Q1,D0_1,
  L1_Q2,L2_Q2,
  L1_Q3,L2_Q3,
  L1_Q4,L2_Q4,
  L1_Q5,L2_Q5,
  L1_Q6,L2_Q6,
  L1_Q7,L2_Q7,
  L1_Q8,L2_Q8,
  L1_Q9,L2_Q9,
  L1_Q10,L2_Q10,
  L1_Q11,L2_Q11,
  L1_Q12,L2_Q12,
  L1_Q13,L2_Q13,
  L1_Q14,L2_Q14,
  L1_Q15,L2_Q15,
  L1_Q16,L2_Q16,
  N);
	signal state, next_state : states := O;
  signal letra : std_logic_vector(7 downto 0);
  signal enviar : std_logic := '1';
  signal data_out : std_logic;
  signal done : std_logic;
  signal signal_ok   : std_logic;
  signal current_state : std_logic_vector(3 downto 0);
  signal state_tx : std_logic_vector(5 downto 0);
  signal next_state_tx : std_logic_vector(5 downto 0);

  signal brg_clock 	: std_logic;
	signal super_clock	: std_logic;
	------------ Alterar o BaudRate aqui caso seja necessário ------------
	signal div 		: integer := 11;
	signal div_vector	: std_logic_vector(15 downto 0);

begin

  control :  control_unit_tx
  port map(super_clock, reset, enviar, letra, data_out, done, current_state);

  --- Instâncias de componentes
	--- Conexões de controle
	div_vector <= std_logic_vector(to_unsigned(div, 16));
	BGR: baud_rate_generator
	port map(clock=>clock, reset=>reset, divisor=>div_vector, baudOut_n=>brg_clock);
	--- Superamostargem
	super: baud_rate_generator
	port map(clock=>brg_clock, reset=>reset, divisor=>"0000000000001111", baudOut_n=>super_clock);

  sout <= data_out;
  ok <= signal_ok;

  with state select
      state_tx <= "000000" when O,
                  "000001" when T,
                  "000010" when L1_Q1,
                  "000011" when L2_Q1,
                  "000100" when D0_1,
                  "000101" when L1_Q2,
                  "000110" when L2_Q2,
                  "000111" when L1_Q3,
                  "001000" when L2_Q3,
                  "001001" when L1_Q4,
                  "001010" when L2_Q4,
                  "001011" when L1_Q5,
                  "001100" when L2_Q5,
                  "001101" when L1_Q6,
                  "001110" when L2_Q6,
                  "001111" when L1_Q7,
                  "010000" when L2_Q7,
                  "010001" when L1_Q8,
                  "010010" when L2_Q8,
                  "010011" when L1_Q9,
                  "010100" when L2_Q9,
                  "010101" when L1_Q10,
                  "010110" when L2_Q10,
                  "010111" when L1_Q11,
                  "011000" when L2_Q11,
                  "011001" when L1_Q12,
                  "011010" when L2_Q12,
                  "011011" when L1_Q13,
                  "011100" when L2_Q13,
                  "011101" when L1_Q14,
                  "011110" when L2_Q14,
                  "011111" when L1_Q15,
                  "100000" when L2_Q15,
                  "100001" when L1_Q16,
                  "100010" when L2_Q16,
                  "100011" when N,
                  "XXXXXX" when others;

  with next_state select
      next_state_tx <= "000000" when O,
                  "000001" when T,
                  "000010" when L1_Q1,
                  "000011" when L2_Q1,
                  "000100" when D0_1,
                  "000101" when L1_Q2,
                  "000110" when L2_Q2,
                  "000111" when L1_Q3,
                  "001000" when L2_Q3,
                  "001001" when L1_Q4,
                  "001010" when L2_Q4,
                  "001011" when L1_Q5,
                  "001100" when L2_Q5,
                  "001101" when L1_Q6,
                  "001110" when L2_Q6,
                  "001111" when L1_Q7,
                  "010000" when L2_Q7,
                  "010001" when L1_Q8,
                  "010010" when L2_Q8,
                  "010011" when L1_Q9,
                  "010100" when L2_Q9,
                  "010101" when L1_Q10,
                  "010110" when L2_Q10,
                  "010111" when L1_Q11,
                  "011000" when L2_Q11,
                  "011001" when L1_Q12,
                  "011010" when L2_Q12,
                  "011011" when L1_Q13,
                  "011100" when L2_Q13,
                  "011101" when L1_Q14,
                  "011110" when L2_Q14,
                  "011111" when L1_Q15,
                  "100000" when L2_Q15,
                  "100001" when L1_Q16,
                  "100010" when L2_Q16,
                  "100011" when N,
                  "XXXXXX" when others; -- Fallback for undefined next_states (highly recommended)

  process(super_clock, reset)
  begin
    if reset = '1' then
      state <= O;
    elsif falling_edge(clock) then
      state <= next_state;
    end if;
  end process;

  process(super_clock, reset)
  begin
    if reset = '1' then
      next_state <= O;
    elsif rising_edge(clock) then
    case state is
      when O =>
        if start = '1' then
          next_state <= T;
        end if;
      when T =>
        letra <= "01010101";
        enviar <= '1';
        next_state <= D0_1;
      when D0_1 =>
          if current_state = "0001" then
            enviar <= '0';
            next_state <= L1_Q1;
          end if;
      when L1_Q1 =>
          if done = '1' then
            letra <= dados(255 downto 248);
            enviar <= '1';
            next_state <= L1_Q2;
          end if;
      when L1_Q2 =>
          if done = '1' then
            letra <= dados(247 downto 240);
            enviar <= '1';
            next_state <= L1_Q3;
          end if;
      when L1_Q3 =>
          if done = '1' then
            letra <= dados(239 downto 232);
            enviar <= '1';
            next_state <= L1_Q4;
          end if;
      when L1_Q4 =>
          if done = '1' then
            letra <= dados(231 downto 224);
            enviar <= '1';
            next_state <= L1_Q5;
          end if;
      when L1_Q5 =>
          if done = '1' then
            letra <= dados(223 downto 216);
            enviar <= '1';
            next_state <= L1_Q6;
          end if;
      when L1_Q6 =>
          if done = '1' then
            letra <= dados(215 downto 208);
            enviar <= '1';
            next_state <= L1_Q7;
          end if;
      when L1_Q7 =>
          if done = '1' then
            letra <= dados(207 downto 200);
            enviar <= '1';
            next_state <= L1_Q8;
          end if;
      when L1_Q8 =>
          if done = '1' then
            letra <= dados(199 downto 192);
            enviar <= '1';
            next_state <= L1_Q9;
          end if;
      when L1_Q9 =>
          if done = '1' then
            letra <= dados(191 downto 184);
            enviar <= '1';
            next_state <= L1_Q10;
          end if;
      when L1_Q10 =>
          if done = '1' then
            letra <= dados(183 downto 176);
            enviar <= '1';
            next_state <= L1_Q11;
          end if;
      when L1_Q11 =>
          if done = '1' then
            letra <= dados(175 downto 168);
            enviar <= '1';
            next_state <= L1_Q12;
          end if;
      when L1_Q12 =>
          if done = '1' then
            letra <= dados(167 downto 160);
            enviar <= '1';
            next_state <= L1_Q13;
          end if;
      when L1_Q13 =>
          if done = '1' then
            letra <= dados(159 downto 152);
            enviar <= '1';
            next_state <= L1_Q14;
          end if;
      when L1_Q14 =>
          if done = '1' then
            letra <= dados(151 downto 144);
            enviar <= '1';
            next_state <= L1_Q15;
          end if;
      when L1_Q15 =>
          if done = '1' then
            letra <= dados(143 downto 136);
            enviar <= '1';
            next_state <= L1_Q16;
          end if;
      when L1_Q16 =>
          if done = '1' then
            letra <= dados(135 downto 128);
            enviar <= '1';
            next_state <= L2_Q1;
          end if;
      when L2_Q1 =>
          if done = '1' then
            letra <= dados(127 downto 120);
            enviar <= '1';
            next_state <= L2_Q2;
          end if;
      when L2_Q2 =>
          if done = '1' then
            letra <= dados(119 downto 112);
            enviar <= '1';
            next_state <= L2_Q3;
          end if;
      when L2_Q3 =>
          if done = '1' then
            letra <= dados(111 downto 104);
            enviar <= '1';
            next_state <= L2_Q4;
          end if;
      when L2_Q4 =>
          if done = '1' then
            letra <= dados(103 downto 96);
            enviar <= '1';
            next_state <= L2_Q5;
          end if;
      when L2_Q5 =>
          if done = '1' then
            letra <= dados(95 downto 88);
            enviar <= '1';
            next_state <= L2_Q6;
          end if;
      when L2_Q6 =>
          if done = '1' then
            letra <= dados(87 downto 80);
            enviar <= '1';
            next_state <= L2_Q7;
          end if;
      when L2_Q7 =>
          if done = '1' then
            letra <= dados(79 downto 72);
            enviar <= '1';
            next_state <= L2_Q8;
          end if;
      when L2_Q8 =>
          if done = '1' then
            letra <= dados(71 downto 64);
            enviar <= '1';
            next_state <= L2_Q9;
          end if;
      when L2_Q9 =>
          if done = '1' then
            letra <= dados(63 downto 56);
            enviar <= '1';
            next_state <= L2_Q10;
          end if;
      when L2_Q10 =>
          if done = '1' then
            letra <= dados(55 downto 48);
            enviar <= '1';
            next_state <= L2_Q11;
          end if;
      when L2_Q11 =>
          if done = '1' then
            letra <= dados(47 downto 40);
            enviar <= '1';
            next_state <= L2_Q12;
          end if;
      when L2_Q12 =>
          if done = '1' then
            letra <= dados(39 downto 32);
            enviar <= '1';
            next_state <= L2_Q13;
          end if;
      when L2_Q13 =>
          if done = '1' then
            letra <= dados(31 downto 24);
            enviar <= '1';
            next_state <= L2_Q14;
          end if;
      when L2_Q14 =>
          if done = '1' then
            letra <= dados(23 downto 16);
            enviar <= '1';
            next_state <= L2_Q15;
          end if;
      when L2_Q15 =>
          if done = '1' then
            letra <= dados(15 downto 8);
            enviar <= '1';
            next_state <= L2_Q16;
          end if;
      when L2_Q16 =>
          if done = '1' then
            letra <= dados(7 downto 0);
            enviar <= '1';
            next_state <= N;
          end if;
      when N =>
          if done = '1' then
            letra <= "10101010";
            enviar <= '1';
            next_state <= O;
            signal_ok <= '1';
          end if;
      end case;
    end if;
  end process;
end architecture;

projeto/testbench/tx_tb.vhd
library ieee;
use ieee.std_logic_1164.all;
use ieee.numeric_std.all;

entity tx_tb is
end tx_tb;

architecture behavioral of tx_tb is

    -- Component Declaration for the UUT (Unit Under Test)
    component tx is
        port (
            clock : in std_logic;
            reset : in std_logic;
            start : in std_logic;
            dados : in std_logic_vector(255 downto 0);
            sout  : out std_logic;
            ok    : out std_logic
        );
    end component;

    -- Signal Declarations
    signal clock_s : std_logic := '0';
    signal reset_s : std_logic := '1'; -- Start with reset active
    signal start_s : std_logic := '0';
    signal dados_s : std_logic_vector(255 downto 0) := (others => '0');
    signal sout_s  : std_logic;
    signal ok_s    : std_logic;

    -- Clock Period Definition
    constant clock_period : time := 542 ns;

begin

    -- Instantiate the Unit Under Test (UUT)
    uut_tx : tx
    port map (
        clock => clock_s,
        reset => reset_s,
        start => start_s,
        dados => dados_s,
        sout  => sout_s,
        ok    => ok_s
    );

    -- Clock Generation Process
    clock_gen : process
    begin
        while true loop
            clock_s <= '0';
            wait for clock_period / 2;
            clock_s <= '1';
            wait for clock_period / 2;
        end loop;
    end process;

    -- Test Stimulus Process
    stimulus : process
    begin
        -- 1. Assert Reset
        reset_s <= '1';
        wait for clock_period * 2; -- Hold reset for a few clock cycles
        reset_s <= '0';            -- Deassert Reset
        wait for clock_period;

        -- 2. Send some data
        dados_s <= (others => '0'); -- Initialize data to all zeros
        wait for clock_period;
        dados_s <= "0100000101000010010000110100010001000101010001100100011101001000010010010100101001001011010011000100110101001110010011110101000001010001010100100101001101010100010101010101011001010111010110000101100101011010010000010100001001000011010001000100010101000110";
        -- You can set more bits of dados_s here for more complex test cases

        start_s <= '1';            -- Assert Start
        --wait for clock_period * 10;     -- Hold start for one clock cycle
        --start_s <= '0';            -- Deassert Start

        -- 3. Wait for 'ok' signal (or a specific duration)
        -- In a real scenario, you'd wait until 'ok_s' becomes '1'
        -- or for a duration long enough for the transmission to complete.
        -- For this example, let's just wait for a fixed duration.
        wait for clock_period * 260; -- Assuming ~256 clock cycles for 256 bits + overhead

        -- 5. End simulation
        wait; -- Wait forever, stopping the simulation
    end process;

end behavioral;

projeto/testbench/waveform.vcd
$date
  Mon Jun  2 11:43:14 2025
$end
$version
  GHDL v0
$end
$timescale
  1 fs
$end
$scope module standard $end
$upscope $end
$scope module std_logic_1164 $end
$upscope $end
$scope module numeric_std $end
$upscope $end
$scope module tx_tb $end
$var reg 1 ! clock_s $end
$var reg 1 " reset_s $end
$var reg 1 # start_s $end
$var reg 256 $ dados_s[255:0] $end
$var reg 1 % sout_s $end
$var reg 1 & ok_s $end
$scope module uut_tx $end
$var reg 1 ' clock $end
$var reg 1 ( reset $end
$var reg 1 ) start $end
$var reg 256 * dados[255:0] $end
$var reg 1 + sout $end
$var reg 1 , ok $end
$comment state is not handled $end
$comment next_state is not handled $end
$var reg 8 - letra[7:0] $end
$var reg 1 . enviar $end
$var reg 1 / data_out $end
$var reg 1 0 done $end
$var reg 1 1 signal_ok $end
$var reg 4 2 current_state[3:0] $end
$var reg 6 3 state_tx[5:0] $end
$var reg 6 4 next_state_tx[5:0] $end
$var reg 1 5 brg_clock $end
$var reg 1 6 super_clock $end
$var integer 32 7 div $end
$var reg 16 8 div_vector[15:0] $end
$scope module control $end
$var reg 1 9 clock $end
$var reg 1 : reset $end
$var reg 1 ; start $end
$var reg 8 < dados[7:0] $end
$var reg 1 = sout $end
$var reg 1 > done $end
$var reg 4 ? current_state[3:0] $end
$var reg 2 @ loadorshift[1:0] $end
$var reg 1 A dados_tx $end
$var reg 1 B serial_i $end
$scope module ttc $end
$var reg 1 C clock $end
$var reg 1 D reset $end
$var reg 1 E start $end
$var reg 2 F regcontrol[1:0] $end
$var reg 1 G serial_i $end
$var reg 1 H done $end
$var reg 4 I current_state[3:0] $end
$comment state is not handled $end
$var reg 2 J rc[1:0] $end
$upscope $end
$scope module reg $end
$var reg 1 K clock $end
$var reg 1 L reset $end
$var reg 2 M loadorshift[1:0] $end
$var reg 1 N serial_i $end
$var reg 8 O data_i[7:0] $end
$var reg 1 P serial_o_r $end
$var reg 1 Q serial_o_l $end
$var reg 8 R reg[7:0] $end
$upscope $end
$upscope $end
$scope module bgr $end
$var reg 1 S clock $end
$var reg 1 T reset $end
$var reg 16 U divisor[15:0] $end
$var reg 1 V baudout_n $end
$var reg 16 W counter[15:0] $end
$var reg 1 X out_clock $end
$upscope $end
$scope module super $end
$var reg 1 Y clock $end
$var reg 1 Z reset $end
$var reg 16 [ divisor[15:0] $end
$var reg 1 \ baudout_n $end
$var reg 16 ] counter[15:0] $end
$var reg 1 ^ out_clock $end
$upscope $end
$upscope $end
$upscope $end
$enddefinitions $end
#0
0!
1"
0#
b0000000000000000000000000000000000000000000000000000000000000000000000000000000000000000000000000000000000000000000000000000000000000000000000000000000000000000000000000000000000000000000000000000000000000000000000000000000000000000000000000000000000000000 $
1%
U&
0'
1(
0)
b0000000000000000000000000000000000000000000000000000000000000000000000000000000000000000000000000000000000000000000000000000000000000000000000000000000000000000000000000000000000000000000000000000000000000000000000000000000000000000000000000000000000000000 *
1+
U,
bUUUUUUUU -
1.
1/
U0
U1
b0000 2
b000000 3
b000000 4
15
16
b1011 7
b0000000000001011 8
19
1:
1;
bUUUUUUUU <
1=
U>
b0000 ?
bUU @
1A
UB
1C
1D
1E
bUU F
UG
UH
b0000 I
bUU J
1K
1L
bUU M
UN
bUUUUUUUU O
1P
1Q
b11111111 R
0S
1T
b0000000000001011 U
1V
b0000000000000000 W
1X
1Y
1Z
b0000000000001111 [
1\
b0000000000000000 ]
1^
#271000000
1!
1'
1S
#542000000
0!
0'
0S
#813000000
1!
1'
1S
#1084000000
0!
0"
0'
0(
0:
0D
0L
0S
0T
0Z
#1355000000
1!
1'
1S
b0000000000000001 W
#1626000000
0!
0'
0S
#1897000000
1!
1'
1S
b0000000000000010 W
#2168000000
0!
1#
b0100000101000010010000110100010001000101010001100100011101001000010010010100101001001011010011000100110101001110010011110101000001010001010100100101001101010100010101010101011001010111010110000101100101011010010000010100001001000011010001000100010101000110 $
0'
1)
b0100000101000010010000110100010001000101010001100100011101001000010010010100101001001011010011000100110101001110010011110101000001010001010100100101001101010100010101010101011001010111010110000101100101011010010000010100001001000011010001000100010101000110 *
0S
#2439000000
1!
1'
1S
b0000000000000011 W
#2710000000
0!
0'
0S
#2981000000
1!
1'
1S
b0000000000000100 W
#3252000000
0!
0'
0S
#3523000000
1!
1'
1S
b0000000000000101 W
#3794000000
0!
0'
0S
#4065000000
1!
1'
05
1S
0V
b0000000000000000 W
0X
0Y
#4336000000
0!
0'
0S
#4607000000
1!
1'
1S
b0000000000000001 W
#4878000000
0!
0'
0S
#5149000000
1!
1'
1S
b0000000000000010 W
#5420000000
0!
0'
0S
#5691000000
1!
1'
1S
b0000000000000011 W
#5962000000
0!
0'
0S
#6233000000
1!
1'
1S
b0000000000000100 W
#6504000000
0!
0'
0S
#6775000000
1!
1'
1S
b0000000000000101 W
#7046000000
0!
0'
0S
#7317000000
1!
1'
15
1S
1V
b0000000000000000 W
1X
1Y
b0000000000000001 ]
#7588000000
0!
0'
0S
#7859000000
1!
1'
1S
b0000000000000001 W
#8130000000
0!
0'
0S
#8401000000
1!
1'
1S
b0000000000000010 W
#8672000000
0!
0'
0S
#8943000000
1!
1'
1S
b0000000000000011 W
#9214000000
0!
0'
0S
#9485000000
1!
1'
1S
b0000000000000100 W
#9756000000
0!
0'
0S
#10027000000
1!
1'
1S
b0000000000000101 W
#10298000000
0!
0'
0S
#10569000000
1!
1'
05
1S
0V
b0000000000000000 W
0X
0Y
#10840000000
0!
0'
0S
#11111000000
1!
1'
1S
b0000000000000001 W
#11382000000
0!
0'
0S
#11653000000
1!
1'
1S
b0000000000000010 W
#11924000000
0!
0'
0S
#12195000000
1!
1'
1S
b0000000000000011 W
#12466000000
0!
0'
0S
#12737000000
1!
1'
1S
b0000000000000100 W
#13008000000
0!
0'
0S
#13279000000
1!
1'
1S
b0000000000000101 W
#13550000000
0!
0'
0S
#13821000000
1!
1'
15
1S
1V
b0000000000000000 W
1X
1Y
b0000000000000010 ]
#14092000000
0!
0'
0S
#14363000000
1!
1'
1S
b0000000000000001 W
#14634000000
0!
0'
0S
#14905000000
1!
1'
1S
b0000000000000010 W
#15176000000
0!
0'
0S
#15447000000
1!
1'
1S
b0000000000000011 W
#15718000000
0!
0'
0S
#15989000000
1!
1'
1S
b0000000000000100 W
#16260000000
0!
0'
0S
#16531000000
1!
1'
1S
b0000000000000101 W
#16802000000
0!
0'
0S
#17073000000
1!
1'
05
1S
0V
b0000000000000000 W
0X
0Y
#17344000000
0!
0'
0S
#17615000000
1!
1'
1S
b0000000000000001 W
#17886000000
0!
0'
0S
#18157000000
1!
1'
1S
b0000000000000010 W
#18428000000
0!
0'
0S
#18699000000
1!
1'
1S
b0000000000000011 W
#18970000000
0!
0'
0S
#19241000000
1!
1'
1S
b0000000000000100 W
#19512000000
0!
0'
0S
#19783000000
1!
1'
1S
b0000000000000101 W
#20054000000
0!
0'
0S
#20325000000
1!
1'
15
1S
1V
b0000000000000000 W
1X
1Y
b0000000000000011 ]
#20596000000
0!
0'
0S
#20867000000
1!
1'
1S
b0000000000000001 W
#21138000000
0!
0'
0S
#21409000000
1!
1'
1S
b0000000000000010 W
#21680000000
0!
0'
0S
#21951000000
1!
1'
1S
b0000000000000011 W
#22222000000
0!
0'
0S
#22493000000
1!
1'
1S
b0000000000000100 W
#22764000000
0!
0'
0S
#23035000000
1!
1'
1S
b0000000000000101 W
#23306000000
0!
0'
0S
#23577000000
1!
1'
05
1S
0V
b0000000000000000 W
0X
0Y
#23848000000
0!
0'
0S
#24119000000
1!
1'
1S
b0000000000000001 W
#24390000000
0!
0'
0S
#24661000000
1!
1'
1S
b0000000000000010 W
#24932000000
0!
0'
0S
#25203000000
1!
1'
1S
b0000000000000011 W
#25474000000
0!
0'
0S
#25745000000
1!
1'
1S
b0000000000000100 W
#26016000000
0!
0'
0S
#26287000000
1!
1'
1S
b0000000000000101 W
#26558000000
0!
0'
0S
#26829000000
1!
1'
15
1S
1V
b0000000000000000 W
1X
1Y
b0000000000000100 ]
#27100000000
0!
0'
0S
#27371000000
1!
1'
1S
b0000000000000001 W
#27642000000
0!
0'
0S
#27913000000
1!
1'
1S
b0000000000000010 W
#28184000000
0!
0'
0S
#28455000000
1!
1'
1S
b0000000000000011 W
#28726000000
0!
0'
0S
#28997000000
1!
1'
1S
b0000000000000100 W
#29268000000
0!
0'
0S
#29539000000
1!
1'
1S
b0000000000000101 W
#29810000000
0!
0'
0S
#30081000000
1!
1'
05
1S
0V
b0000000000000000 W
0X
0Y
#30352000000
0!
0'
0S
#30623000000
1!
1'
1S
b0000000000000001 W
#30894000000
0!
0'
0S
#31165000000
1!
1'
1S
b0000000000000010 W
#31436000000
0!
0'
0S
#31707000000
1!
1'
1S
b0000000000000011 W
#31978000000
0!
0'
0S
#32249000000
1!
1'
1S
b0000000000000100 W
#32520000000
0!
0'
0S
#32791000000
1!
1'
1S
b0000000000000101 W
#33062000000
0!
0'
0S
#33333000000
1!
1'
15
1S
1V
b0000000000000000 W
1X
1Y
b0000000000000101 ]
#33604000000
0!
0'
0S
#33875000000
1!
1'
1S
b0000000000000001 W
#34146000000
0!
0'
0S
#34417000000
1!
1'
1S
b0000000000000010 W
#34688000000
0!
0'
0S
#34959000000
1!
1'
1S
b0000000000000011 W
#35230000000
0!
0'
0S
#35501000000
1!
1'
1S
b0000000000000100 W
#35772000000
0!
0'
0S
#36043000000
1!
1'
1S
b0000000000000101 W
#36314000000
0!
0'
0S
#36585000000
1!
1'
05
1S
0V
b0000000000000000 W
0X
0Y
#36856000000
0!
0'
0S
#37127000000
1!
1'
1S
b0000000000000001 W
#37398000000
0!
0'
0S
#37669000000
1!
1'
1S
b0000000000000010 W
#37940000000
0!
0'
0S
#38211000000
1!
1'
1S
b0000000000000011 W
#38482000000
0!
0'
0S
#38753000000
1!
1'
1S
b0000000000000100 W
#39024000000
0!
0'
0S
#39295000000
1!
1'
1S
b0000000000000101 W
#39566000000
0!
0'
0S
#39837000000
1!
1'
15
1S
1V
b0000000000000000 W
1X
1Y
b0000000000000110 ]
#40108000000
0!
0'
0S
#40379000000
1!
1'
1S
b0000000000000001 W
#40650000000
0!
0'
0S
#40921000000
1!
1'
1S
b0000000000000010 W
#41192000000
0!
0'
0S
#41463000000
1!
1'
1S
b0000000000000011 W
#41734000000
0!
0'
0S
#42005000000
1!
1'
1S
b0000000000000100 W
#42276000000
0!
0'
0S
#42547000000
1!
1'
1S
b0000000000000101 W
#42818000000
0!
0'
0S
#43089000000
1!
1'
05
1S
0V
b0000000000000000 W
0X
0Y
#43360000000
0!
0'
0S
#43631000000
1!
1'
1S
b0000000000000001 W
#43902000000
0!
0'
0S
#44173000000
1!
1'
1S
b0000000000000010 W
#44444000000
0!
0'
0S
#44715000000
1!
1'
1S
b0000000000000011 W
#44986000000
0!
0'
0S
#45257000000
1!
1'
1S
b0000000000000100 W
#45528000000
0!
0'
0S
#45799000000
1!
1'
1S
b0000000000000101 W
#46070000000
0!
0'
0S
#46341000000
1!
1'
15
1S
1V
b0000000000000000 W
1X
1Y
b0000000000000111 ]
#46612000000
0!
0'
0S
#46883000000
1!
1'
1S
b0000000000000001 W
#47154000000
0!
0'
0S
#47425000000
1!
1'
1S
b0000000000000010 W
#47696000000
0!
0'
0S
#47967000000
1!
1'
1S
b0000000000000011 W
#48238000000
0!
0'
0S
#48509000000
1!
1'
1S
b0000000000000100 W
#48780000000
0!
0'
0S
#49051000000
1!
1'
1S
b0000000000000101 W
#49322000000
0!
0'
0S
#49593000000
1!
1'
05
1S
0V
b0000000000000000 W
0X
0Y
#49864000000
0!
0'
0S
#50135000000
1!
1'
1S
b0000000000000001 W
#50406000000
0!
0'
0S
#50677000000
1!
1'
1S
b0000000000000010 W
#50948000000
0!
0'
0S
#51219000000
1!
1'
1S
b0000000000000011 W
#51490000000
0!
0'
0S
#51761000000
1!
1'
1S
b0000000000000100 W
#52032000000
0!
0'
0S
#52303000000
1!
1'
1S
b0000000000000101 W
#52574000000
0!
0'
0S
#52845000000
1!
1'
00
b0001 2
15
06
09
0>
b0001 ?
b00 @
0C
b00 F
0H
b0001 I
b00 J
0K
b00 M
1S
1V
b0000000000000000 W
1X
1Y
0\
b0000000000000000 ]
0^
#53116000000
0!
0'
0S
#53387000000
1!
1'
1S
b0000000000000001 W
#53658000000
0!
0'
0S
#53929000000
1!
1'
1S
b0000000000000010 W
#54200000000
0!
0'
0S
